setup.cfg
setup.py
pifacecommon/__init__.py
pifacecommon/asm_generic_ioctl.py
pifacecommon/core.py
pifacecommon/interrupts.py
pifacecommon.egg-info/PKG-INFO
pifacecommon.egg-info/SOURCES.txt
pifacecommon.egg-info/dependency_links.txt
pifacecommon.egg-info/requires.txt
pifacecommon.egg-info/top_level.txt