Metadata-Version: 1.1
Name: pifacecommon
Version: 1.1
Summary: The PiFace common functions module.
Home-page: https://github.com/piface/pifacecommon
Author: Thomas Preston
Author-email: thomasmarkpreston@gmail.com
License: GPLv3+
Keywords: piface raspberrypi openlx
Platform: UNKNOWN
Classifier: License :: OSI Approved :: GNU Affero General Public License v3 or later (AGPLv3+)
Classifier: Programming Language :: Python :: 3
Classifier: Development Status :: 5 - Production/Stable
Classifier: Intended Audience :: Developers
Classifier: Topic :: Software Development :: Libraries :: Python Modules
